nose_html_report/html_reporter.py
nose_html_report/__init__.py
nose_html_report/html/jquery-2.1.1.js
nose_html_report/html/nosetests.css
nose_html_report/html/nosetests.jinja2
nose_html_report/html/nosetests.js
nose_html_report/html/pygments.css
nose_html_report/html/reset.css
nose_html_report-0.1.dist-info/DESCRIPTION.rst
nose_html_report-0.1.dist-info/entry_points.txt
nose_html_report-0.1.dist-info/METADATA
nose_html_report-0.1.dist-info/metadata.json
nose_html_report-0.1.dist-info/RECORD
nose_html_report-0.1.dist-info/top_level.txt
nose_html_report-0.1.dist-info/WHEEL
