Metadata-Version: 2.0
Name: nose-html-report
Version: 0.1
Summary: A nose plugin to generate good-looking HTML reports for tests.
Home-page: https://github.com/pradyun/nose-html-report
Author: Pradyun S. Gedam
Author-email: pradyunsg@gmail.com
License: UNKNOWN
Platform: UNKNOWN
Classifier: Intended Audience :: Developers
Classifier: Topic :: Software Development :: Testing
Requires-Dist: Jinja2
Requires-Dist: nose
Requires-Dist: Pygments
